Workbook

Sheet README
A1: Dementia Voice Assistant — Pricing & Sensitivity Analysis
A3: Purpose
A4: A premium voice assistant backed by the 'Understanding Dementia' textbook (15 chapters, 200-concept learning graph) targeted at caregivers and families. This workbook models the economics under realistic usage so you can decide pricing, platform, and break-even point.
A6: How to use this workbook
A7: 1. Open the 'Assumptions' sheet. Yellow cells are inputs — edit them. Everything else recomputes.
A8: 2. 'Unit Economics' shows what one subscriber costs to serve, by platform.
A9: 3. 'Session Mix' models a real caregiver's monthly usage pattern (mix of quick lookups + longer sessions).
A10: 4. 'Sensitivity' is the most important sheet: a 2D table of (subscribers × monthly-usage) showing monthly profit/loss.
A11: 5. '12-Month Projection' compares two growth scenarios under both platforms.
A12: 6. Color coding: yellow = editable input, blue = calculated cell, dark headers = labels.
A14: Key assumptions baked in (change in 'Assumptions' sheet)
A15: • ElevenLabs Agents conversation cost: $0.10/min (mid of empirical $0.08–0.12 range).
... A33: • Empirical conversation lengths from ElevenLabs dashboard (Distracted Driving Tutor, 3 sessions): 76s, 177s, 338s — mean ~2.7 min per session.

Sheet Assumptions
A1: Assumptions (yellow cells = editable)
A3: PLATFORM COSTS
A4: ElevenLabs Agents — per minute cost ($) | B4: 0.1 | C4: Mid of empirical $0.08–0.12 range
A5: OpenAI Realtime — per minute cost ($) | B5: 0.3 | C5: Empirical 2026-05-08: $0.87 / 2.9 min
A6: ElevenLabs Enterprise + BAA fixed monthly ($) | B6: 1250 | C6: Required for HIPAA / PHI handling
A7: Domain + hosting + monitoring monthly ($) | B7: 50 | C7: Vercel + a status page + analytics
A8: Customer support tooling monthly ($) | B8: 100 | C8: Intercom/Help Scout + transcript review tools
A11: SUBSCRIPTION PRICING
A12: Monthly subscription price ($) | B12: 14.99 | C12: Premium positioning vs free Alzheimer's hotlines
A13: Minutes included per month | B13: 45 | C13: Caps cost exposure; ~3-4 caregiver sessions
A14: Stripe fee — percentage | B14: 0.029 | C14: Standard online rate
A15: Stripe fee — fixed per transaction ($) | B15: 0.3 | C15: Per successful charge
A18: AVERAGE SUBSCRIBER USAGE PATTERN
A19: Avg minutes used per subscriber per month | B19: 28 | C19: Heavy users hit the 45-min cap; many use less
A20: % of users who hit the cap | B20: 0.2 | C20: Drives whether to raise cap or upsell tier

Sheet Unit Economics
A1: Unit Economics — one subscriber, one month
A3: Metric | B3: ElevenLabs Agents | C3: OpenAI Realtime
A4: Revenue per subscriber ($) | B4: =Assumptions!$B$12 | C4: =Assumptions!$B$12
A5: Stripe processing fee ($) | B5: =-(Assumptions!$B$12*Assumptions!$B$14+Assumptions!$B$15) | C5: =-(Assumptions!$B$12*Assumptions!$B$14+Assumptions!$B$15)
A6: Avg minutes used per month | B6: =Assumptions!$B$19 | C6: =Assumptions!$B$19
A7: Variable cost — conversation ($) | B7: =-Assumptions!$B$19*Assumptions!$B$4 | C7: =-Assumptions!$B$19*Assumptions!$B$5
A8: Contribution margin per subscriber ($) | B8: =B4+B5+B7 | C8: =C4+C5+C7
A9: Contribution margin % | B9: =B8/B4 | C9: =C8/C4
A11: Read: this is the gross variable margin before fixed costs (Enterprise/BAA, hosting, support, salaries).
A13: Worst case (subscriber uses full 45-min cap)
A14: Revenue ($) | B14: =Assumptions!$B$12 | C14: =Assumptions!$B$12
A15: Stripe fee ($) | B15: =-(Assumptions!$B$12*Assumptions!$B$14+Assumptions!$B$15) | C15: =-(Assumptions!$B$12*Assumptions!$B$14+Assumptions!$B$15)
A16: Minutes (at cap) | B16: =Assumptions!$B$13 | C16: =Assumptions!$B$13
A17: Variable cost ($) | B17: =-Assumptions!$B$13*Assumptions!$B$4 | C17: =-Assumptions!$B$13*Assumptions!$B$5
A18: Margin at cap ($) | B18: =B14+B15+B17 | C18: =C14+C15+C17
A19: Margin at cap % | B19: =B18/B14 | C19: =C18/C14
A21: Key insight: if a heavy user maxes the cap on OpenAI Realtime, you lose money on them. On ElevenLabs, margin stays positive even at full usage.

Sheet Session Mix
A1: Session Mix — what does an active caregiver subscriber actually do?
A3: Session type | B3: Avg duration (min) | C3: Frequency/month | D3: Minutes/month | E3: ElevenLabs cost | F3: OpenAI Realtime cost
A4: Quick lookup ('what is sundowning?') | B4: 2 | C4: 6 | D4: =B4*C4 | E4: =D4*Assumptions!$B$4 | F4: =D4*Assumptions!$B$5
A5: Caregiver problem-solving conversation | B5: 10 | C5: 2 | D5: =B5*C5 | E5: =D5*Assumptions!$B$4 | F5: =D5*Assumptions!$B$5
A6: Patient walkthrough of new diagnosis | B6: 20 | C6: 0.5 | D6: =B6*C6 | E6: =D6*Assumptions!$B$4 | F6: =D6*Assumptions!$B$5
A7: 3am crisis call (wandering, fall, agitation) | B7: 15 | C7: 0.3 | D7: =B7*C7 | E7: =D7*Assumptions!$B$4 | F7: =D7*Assumptions!$B$5
A8: Daily check-in / emotional support | B8: 5 | C8: 4 | D8: =B8*C8 | E8: =D8*Assumptions!$B$4 | F8: =D8*Assumptions!$B$5
A9: TOTAL | D9: =SUM(D4:D8) | E9: =SUM(E4:E8) | F9: =SUM(F4:F8)
A11: Implied avg minutes per active sub | B11: =D9
A12: Implied variable cost per active sub (ElevenLabs) | B12: =E9
A13: Implied variable cost per active sub (OpenAI Realtime) | B13: =F9
A15: Edit yellow cells to model different user behavior. If your implied minutes here differ from the 'avg minutes' in Assumptions, the Assumptions value is the one that drives the Sensitivity sheet — update Assumptions to match.

Sheet Sensitivity
A1: Sensitivity — monthly profit/loss by (subscribers × avg usage)
A3: Each cell = monthly net profit. Includes variable conversation cost, Stripe fees, and fixed costs (Enterprise + hosting + support). NEGATIVE = losing money at that scale.
A5: (A) ElevenLabs Agents — NO Enterprise/BAA (educational only, no PHI)
A6: Avg min/sub ↓ | Subscribers → | B6: 25 | C6: 50 | D6: 100 | E6: 200 | F6: 400 | G6: 800 | H6: 1500 | I6: 3000 | J6: 5000
A7: 10 | B7: =25*Assumptions!$B$12-25*(Assumptions!$B$12*Assumptions!$B$14+Assumptions!$B$15)-25*10*Assumptions!$B$4-(Assumptions!$B$7+Assumptions!$B$8) | C7: =50*Assumptions!$B$12-50*(Assumptions!$B$12*Assumptions!$B$14+Assumptions!$B$15)-50*10*Assumptions!$B$4-(Assumptions!$B$7+Assumptions!$B$8) | D7: =100*Assumptions!$B$12-100*(Assumptions!$B$12*Assumptions!$B$14+Assumptions!$B$15)-100*10*Assumptions!$B$4-(Assumptions!$B$7+Assumptions!$B$8) | E7: =200*Assumptions!$B$12-200*(Assumptions!$B$12*Assumptions!$B$14+Assumptions!$B$15)-200*10*Assumptions!$B$4-(Assumptions!$B$7+Assumptions!$B$8) | F7: =400*Assumptions!$B$12-400*(Assumptions!$B$12*Assumptions!$B$14+Assumptions!$B$15)-400*10*Assumptions!$B$4-(Assumptions!$B$7+Assumptions!$B$8) | G7: =800*Assumptions!$B$12-800*(Assumptions!$B$12*Assumptions!$B$14+Assumptions!$B$15)-800*10*Assumptions!$B$4-(Assumptions!$B$7+Assumptions!$B$8) | H7: =1500*Assumptions!$B$12-1500*(Assumptions!$B$12*Assumptions!$B$14+Assumptions!$B$15)-1500*10*Assumptions!$B$4-(Assumptions!$B$7+Assumptions!$B$8) | I7: =3000*Assumptions!$B$12-3000*(Assumptions!$B$12*Assumptions!$B$14+Assumptions!$B$15)-3000*10*Assumptions!$B$4-(Assumptions!$B$7+Assumptions!$B$8) | J7: =5000*Assumptions!$B$12-5000*(Assumptions!$B$12*Assumptions!$B$14+Assumptions!$B$15)-5000*10*Assumptions!$B$4-(Assumptions!$B$7+Assumptions!$B$8)
A8: 15 | B8: =25*Assumptions!$B$12-25*(Assumptions!$B$12*Assumptions!$B$14+Assumptions!$B$15)-25*15*Assumptions!$B$4-(Assumptions!$B$7+Assumptions!$B$8) | C8: =50*Assumptions!$B$12-50*(Assumptions!$B$12*Assumptions!$B$14+Assumptions!$B$15)-50*15*Assumptions!$B$4-(Assumptions!$B$7+Assumptions!$B$8) | D8: =100*Assumptions!$B$12-100*(Assumptions!$B$12*Assumptions!$B$14+Assumptions!$B$15)-100*15*Assumptions!$B$4-(Assumptions!$B$7+Assumptions!$B$8) | E8: =200*Assumptions!$B$12-200*(Assumptions!$B$12*Assumptions!$B$14+Assumptions!$B$15)-200*15*Assumptions!$B$4-(Assumptions!$B$7+Assumptions!$B$8) | F8: =400*Assumptions!$B$12-400*(Assumptions!$B$12*Assumptions!$B$14+Assumptions!$B$15)-400*15*Assumptions!$B$4-(Assumptions!$B$7+Assumptions!$B$8) | G8: =800*Assumptions!$B$12-800*(Assumptions!$B$12*Assumptions!$B$14+Assumptions!$B$15)-800*15*Assumptions!$B$4-(Assumptions!$B$7+Assumptions!$B$8) | H8: =1500*Assumptions!$B$12-1500*(Assumptions!$B$12*Assumptions!$B$14+Assumptions!$B$15)-1500*15*Assumptions!$B$4-(Assumptions!$B$7+Assumptions!$B$8) | I8: =3000*Assumptions!$B$12-3000*(Assumptions!$B$12*Assumptions!$B$14+Assumptions!$B$15)-3000*15*Assumptions!$B$4-(Assumptions!$B$7+Assumptions!$B$8) | J8: =5000*Assumptions!$B$12-5000*(Assumptions!$B$12*Assumptions!$B$14+Assumptions!$B$15)-5000*15*Assumptions!$B$4-(Assumptions!$B$7+Assumptions!$B$8)
A9: 20 | B9: =25*Assumptions!$B$12-25*(Assumptions!$B$12*Assumptions!$B$14+Assumptions!$B$15)-25*20*Assumptions!$B$4-(Assumptions!$B$7+Assumptions!$B$8) | C9: =50*Assumptions!$B$12-50*(Assumptions!$B$12*Assumptions!$B$14+Assumptions!$B$15)-50*20*Assumptions!$B$4-(Assumptions!$B$7+Assumptions!$B$8) | D9: =100*Assumptions!$B$12-100*(Assumptions!$B$12*Assumptions!$B$14+Assumptions!$B$15)-100*20*Assumptions!$B$4-(Assumptions!$B$7+Assumptions!$B$8) | E9: =200*Assumptions!$B$12-200*(Assumptions!$B$12*Assumptions!$B$14+Assumptions!$B$15)-200*20*Assumptions!$B$4-(Assumptions!$B$7+Assumptions!$B$8) | F9: =400*Assumptions!$B$12-400*(Assumptions!$B$12*Assumptions!$B$14+Assumptions!$B$15)-400*20*Assumptions!$B$4-(Assumptions!$B$7+Assumptions!$B$8) | G9: =800*Assumptions!$B$12-800*(Assumptions!$B$12*Assumptions!$B$14+Assumptions!$B$15)-800*20*Assumptions!$B$4-(Assumptions!$B$7+Assumptions!$B$8) | H9: =1500*Assumptions!$B$12-1500*(Assumptions!$B$12*Assumptions!$B$14+Assumptions!$B$15)-1500*20*Assumptions!$B$4-(Assumptions!$B$7+Assumptions!$B$8) | I9: =3000*Assumptions!$B$12-3000*(Assumptions!$B$12*Assumptions!$B$14+Assumptions!$B$15)-3000*20*Assumptions!$B$4-(Assumptions!$B$7+Assumptions!$B$8) | J9: =5000*Assumptions!$B$12-5000*(Assumptions!$B$12*Assumptions!$B$14+Assumptions!$B$15)-5000*20*Assumptions!$B$4-(Assumptions!$B$7+Assumptions!$B$8)
A10: 25 | B10: =25*Assumptions!$B$12-25*(Assumptions!$B$12*Assumptions!$B$14+Assumptions!$B$15)-25*25*Assumptions!$B$4-(Assumptions!$B$7+Assumptions!$B$8) | C10: =50*Assumptions!$B$12-50*(Assumptions!$B$12*Assumptions!$B$14+Assumptions!$B$15)-50*25*Assumptions!$B$4-(Assumptions!$B$7+Assumptions!$B$8) | D10: =100*Assumptions!$B$12-100*(Assumptions!$B$12*Assumptions!$B$14+Assumptions!$B$15)-100*25*Assumptions!$B$4-(Assumptions!$B$7+Assumptions!$B$8) | E10: =200*Assumptions!$B$12-200*(Assumptions!$B$12*Assumptions!$B$14+Assumptions!$B$15)-200*25*Assumptions!$B$4-(Assumptions!$B$7+Assumptions!$B$8) | F10: =400*Assumptions!$B$12-400*(Assumptions!$B$12*Assumptions!$B$14+Assumptions!$B$15)-400*25*Assumptions!$B$4-(Assumptions!$B$7+Assumptions!$B$8) | G10: =800*Assumptions!$B$12-800*(Assumptions!$B$12*Assumptions!$B$14+Assumptions!$B$15)-800*25*Assumptions!$B$4-(Assumptions!$B$7+Assumptions!$B$8) | H10: =1500*Assumptions!$B$12-1500*(Assumptions!$B$12*Assumptions!$B$14+Assumptions!$B$15)-1500*25*Assumptions!$B$4-(Assumptions!$B$7+Assumptions!$B$8) | I10: =3000*Assumptions!$B$12-3000*(Assumptions!$B$12*Assumptions!$B$14+Assumptions!$B$15)-3000*25*Assumptions!$B$4-(Assumptions!$B$7+Assumptions!$B$8) | J10: =5000*Assumptions!$B$12-5000*(Assumptions!$B$12*Assumptions!$B$14+Assumptions!$B$15)-5000*25*Assumptions!$B$4-(Assumptions!$B$7+Assumptions!$B$8)
A11: 30 | B11: =25*Assumptions!$B$12-25*(Assumptions!$B$12*Assumptions!$B$14+Assumptions!$B$15)-25*30*Assumptions!$B$4-(Assumptions!$B$7+Assumptions!$B$8) | C11: =50*Assumptions!$B$12-50*(Assumptions!$B$12*Assumptions!$B$14+Assumptions!$B$15)-50*30*Assumptions!$B$4-(Assumptions!$B$7+Assumptions!$B$8) | D11: =100*Assumptions!$B$12-100*(Assumptions!$B$12*Assumptions!$B$14+Assumptions!$B$15)-100*30*Assumptions!$B$4-(Assumptions!$B$7+Assumptions!$B$8) | E11: =200*Assumptions!$B$12-200*(Assumptions!$B$12*Assumptions!$B$14+Assumptions!$B$15)-200*30*Assumptions!$B$4-(Assumptions!$B$7+Assumptions!$B$8) | F11: =400*Assumptions!$B$12-400*(Assumptions!$B$12*Assumptions!$B$14+Assumptions!$B$15)-400*30*Assumptions!$B$4-(Assumptions!$B$7+Assumptions!$B$8) | G11: =800*Assumptions!$B$12-800*(Assumptions!$B$12*Assumptions!$B$14+Assumptions!$B$15)-800*30*Assumptions!$B$4-(Assumptions!$B$7+Assumptions!$B$8) | H11: =1500*Assumptions!$B$12-1500*(Assumptions!$B$12*Assumptions!$B$14+Assumptions!$B$15)-1500*30*Assumptions!$B$4-(Assumptions!$B$7+Assumptions!$B$8) | I11: =3000*Assumptions!$B$12-3000*(Assumptions!$B$12*Assumptions!$B$14+Assumptions!$B$15)-3000*30*Assumptions!$B$4-(Assumptions!$B$7+Assumptions!$B$8) | J11: =5000*Assumptions!$B$12-5000*(Assumptions!$B$12*Assumptions!$B$14+Assumptions!$B$15)-5000*30*Assumptions!$B$4-(Assumptions!$B$7+Assumptions!$B$8)
A12: 35 | B12: =25*Assumptions!$B$12-25*(Assumptions!$B$12*Assumptions!$B$14+Assumptions!$B$15)-25*35*Assumptions!$B$4-(Assumptions!$B$7+Assumptions!$B$8) | C12: =50*Assumptions!$B$12-50*(Assumptions!$B$12*Assumptions!$B$14+Assumptions!$B$15)-50*35*Assumptions!$B$4-(Assumptions!$B$7+Assumptions!$B$8) | D12: =100*Assumptions!$B$12-100*(Assumptions!$B$12*Assumptions!$B$14+Assumptions!$B$15)-100*35*Assumptions!$B$4-(Assumptions!$B$7+Assumptions!$B$8) | E12: =200*Assumptions!$B$12-200*(Assumptions!$B$12*Assumptions!$B$14+Assumptions!$B$15)-200*35*Assumptions!$B$4-(Assumptions!$B$7+Assumptions!$B$8) | F12: =400*Assumptions!$B$12-400*(Assumptions!$B$12*Assumptions!$B$14+Assumptions!$B$15)-400*35*Assumptions!$B$4-(Assumptions!$B$7+Assumptions!$B$8) | G12: =800*Assumptions!$B$12-800*(Assumptions!$B$12*Assumptions!$B$14+Assumptions!$B$15)-800*35*Assumptions!$B$4-(Assumptions!$B$7+Assumptions!$B$8) | H12: =1500*Assumptions!$B$12-1500*(Assumptions!$B$12*Assumptions!$B$14+Assumptions!$B$15)-1500*35*Assumptions!$B$4-(Assumptions!$B$7+Assumptions!$B$8) | I12: =3000*Assumptions!$B$12-3000*(Assumptions!$B$12*Assumptions!$B$14+Assumptions!$B$15)-3000*35*Assumptions!$B$4-(Assumptions!$B$7+Assumptions!$B$8) | J12: =5000*Assumptions!$B$12-5000*(Assumptions!$B$12*Assumptions!$B$14+Assumptions!$B$15)-5000*35*Assumptions!$B$4-(Assumptions!$B$7+Assumptions!$B$8)
A13: 40 | B13: =25*Assumptions!$B$12-25*(Assumptions!$B$12*Assumptions!$B$14+Assumptions!$B$15)-25*40*Assumptions!$B$4-(Assumptions!$B$7+Assumptions!$B$8) | C13: =50*Assumptions!$B$12-50*(Assumptions!$B$12*Assumptions!$B$14+Assumptions!$B$15)-50*40*Assumptions!$B$4-(Assumptions!$B$7+Assumptions!$B$8) | D13: =100*Assumptions!$B$12-100*(Assumptions!$B$12*Assumptions!$B$14+Assumptions!$B$15)-100*40*Assumptions!$B$4-(Assumptions!$B$7+Assumptions!$B$8) | E13: =200*Assumptions!$B$12-200*(Assumptions!$B$12*Assumptions!$B$14+Assumptions!$B$15)-200*40*Assumptions!$B$4-(Assumptions!$B$7+Assumptions!$B$8) | F13: =400*Assumptions!$B$12-400*(Assumptions!$B$12*Assumptions!$B$14+Assumptions!$B$15)-400*40*Assumptions!$B$4-(Assumptions!$B$7+Assumptions!$B$8) | G13: =800*Assumptions!$B$12-800*(Assumptions!$B$12*Assumptions!$B$14+Assumptions!$B$15)-800*40*Assumptions!$B$4-(Assumptions!$B$7+Assumptions!$B$8) | H13: =1500*Assumptions!$B$12-1500*(Assumptions!$B$12*Assumptions!$B$14+Assumptions!$B$15)-1500*40*Assumptions!$B$4-(Assumptions!$B$7+Assumptions!$B$8) | I13: =3000*Assumptions!$B$12-3000*(Assumptions!$B$12*Assumptions!$B$14+Assumptions!$B$15)-3000*40*Assumptions!$B$4-(Assumptions!$B$7+Assumptions!$B$8) | J13: =5000*Assumptions!$B$12-5000*(Assumptions!$B$12*Assumptions!$B$14+Assumptions!$B$15)-5000*40*Assumptions!$B$4-(Assumptions!$B$7+Assumptions!$B$8)
A14: 45 | B14: =25*Assumptions!$B$12-25*(Assumptions!$B$12*Assumptions!$B$14+Assumptions!$B$15)-25*45*Assumptions!$B$4-(Assumptions!$B$7+Assumptions!$B$8) | C14: =50*Assumptions!$B$12-50*(Assumptions!$B$12*Assumptions!$B$14+Assumptions!$B$15)-50*45*Assumptions!$B$4-(Assumptions!$B$7+Assumptions!$B$8) | D14: =100*Assumptions!$B$12-100*(Assumptions!$B$12*Assumptions!$B$14+Assumptions!$B$15)-100*45*Assumptions!$B$4-(Assumptions!$B$7+Assumptions!$B$8) | E14: =200*Assumptions!$B$12-200*(Assumptions!$B$12*Assumptions!$B$14+Assumptions!$B$15)-200*45*Assumptions!$B$4-(Assumptions!$B$7+Assumptions!$B$8) | F14: =400*Assumptions!$B$12-400*(Assumptions!$B$12*Assumptions!$B$14+Assumptions!$B$15)-400*45*Assumptions!$B$4-(Assumptions!$B$7+Assumptions!$B$8) | G14: =800*Assumptions!$B$12-800*(Assumptions!$B$12*Assumptions!$B$14+Assumptions!$B$15)-800*45*Assumptions!$B$4-(Assumptions!$B$7+Assumptions!$B$8) | H14: =1500*Assumptions!$B$12-1500*(Assumptions!$B$12*Assumptions!$B$14+Assumptions!$B$15)-1500*45*Assumptions!$B$4-(Assumptions!$B$7+Assumptions!$B$8) | I14: =3000*Assumptions!$B$12-3000*(Assumptions!$B$12*Assumptions!$B$14+Assumptions!$B$15)-3000*45*Assumptions!$B$4-(Assumptions!$B$7+Assumptions!$B$8) | J14: =5000*Assumptions!$B$12-5000*(Assumptions!$B$12*Assumptions!$B$14+Assumptions!$B$15)-5000*45*Assumptions!$B$4-(Assumptions!$B$7+Assumptions!$B$8)
A17: (B) ElevenLabs Agents — WITH Enterprise + BAA ($1250/mo fixed)
A18: Avg min/sub ↓ | Subscribers → | B18: 25 | C18: 50 | D18: 100 | E18: 200 | F18: 400 | G18: 800 | H18: 1500 | I18: 3000 | J18: 5000
A19: 10 | B19: =25*Assumptions!$B$12-25*(Assumptions!$B$12*Assumptions!$B$14+Assumptions!$B$15)-25*10*Assumptions!$B$4-(Assumptions!$B$6+Assumptions!$B$7+Assumptions!$B$8) | C19: =50*Assumptions!$B$12-50*(Assumptions!$B$12*Assumptions!$B$14+Assumptions!$B$15)-50*10*Assumptions!$B$4-(Assumptions!$B$6+Assumptions!$B$7+Assumptions!$B$8) | D19: =100*Assumptions!$B$12-100*(Assumptions!$B$12*Assumptions!$B$14+Assumptions!$B$15)-100*10*Assumptions!$B$4-(Assumptions!$B$6+Assumptions!$B$7+Assumptions!$B$8) | E19: =200*Assumptions!$B$12-200*(Assumptions!$B$12*Assumptions!$B$14+Assumptions!$B$15)-200*10*Assumptions!$B$4-(Assumptions!$B$6+Assumptions!$B$7+Assumptions!$B$8) | F19: =400*Assumptions!$B$12-400*(Assumptions!$B$12*Assumptions!$B$14+Assumptions!$B$15)-400*10*Assumptions!$B$4-(Assumptions!$B$6+Assumptions!$B$7+Assumptions!$B$8) | G19: =800*Assumptions!$B$12-800*(Assumptions!$B$12*Assumptions!$B$14+Assumptions!$B$15)-800*10*Assumptions!$B$4-(Assumptions!$B$6+Assumptions!$B$7+Assumptions!$B$8) | H19: =1500*Assumptions!$B$12-1500*(Assumptions!$B$12*Assumptions!$B$14+Assumptions!$B$15)-1500*10*Assumptions!$B$4-(Assumptions!$B$6+Assumptions!$B$7+Assumptions!$B$8) | I19: =3000*Assumptions!$B$12-3000*(Assumptions!$B$12*Assumptions!$B$14+Assumptions!$B$15)-3000*10*Assumptions!$B$4-(Assumptions!$B$6+Assumptions!$B$7+Assumptions!$B$8) | J19: =5000*Assumptions!$B$12-5000*(Assumptions!$B$12*Assumptions!$B$14+Assumptions!$B$15)-5000*10*Assumptions!$B$4-(Assumptions!$B$6+Assumptions!$B$7+Assumptions!$B$8)
A20: 15 | B20: =25*Assumptions!$B$12-25*(Assumptions!$B$12*Assumptions!$B$14+Assumptions!$B$15)-25*15*Assumptions!$B$4-(Assumptions!$B$6+Assumptions!$B$7+Assumptions!$B$8) | C20: =50*Assumptions!$B$12-50*(Assumptions!$B$12*Assumptions!$B$14+Assumptions!$B$15)-50*15*Assumptions!$B$4-(Assumptions!$B$6+Assumptions!$B$7+Assumptions!$B$8) | D20: =100*Assumptions!$B$12-100*(Assumptions!$B$12*Assumptions!$B$14+Assumptions!$B$15)-100*15*Assumptions!$B$4-(Assumptions!$B$6+Assumptions!$B$7+Assumptions!$B$8) | E20: =200*Assumptions!$B$12-200*(Assumptions!$B$12*Assumptions!$B$14+Assumptions!$B$15)-200*15*Assumptions!$B$4-(Assumptions!$B$6+Assumptions!$B$7+Assumptions!$B$8) | F20: =400*Assumptions!$B$12-400*(Assumptions!$B$12*Assumptions!$B$14+Assumptions!$B$15)-400*15*Assumptions!$B$4-(Assumptions!$B$6+Assumptions!$B$7+Assumptions!$B$8) | G20: =800*Assumptions!$B$12-800*(Assumptions!$B$12*Assumptions!$B$14+Assumptions!$B$15)-800*15*Assumptions!$B$4-(Assumptions!$B$6+Assumptions!$B$7+Assumptions!$B$8) | H20: =1500*Assumptions!$B$12-1500*(Assumptions!$B$12*Assumptions!$B$14+Assumptions!$B$15)-1500*15*Assumptions!$B$4-(Assumptions!$B$6+Assumptions!$B$7+Assumptions!$B$8) | I20: =3000*Assumptions!$B$12-3000*(Assumptions!$B$12*Assumptions!$B$14+Assumptions!$B$15)-3000*15*Assumptions!$B$4-(Assumptions!$B$6+Assumptions!$B$7+Assumptions!$B$8) | J20: =5000*Assumptions!$B$12-5000*(Assumptions!$B$12*Assumptions!$B$14+Assumptions!$B$15)-5000*15*Assumptions!$B$4-(Assumptions!$B$6+Assumptions!$B$7+Assumptions!$B$8)
A21: 20 | B21: =25*Assumptions!$B$12-25*(Assumptions!$B$12*Assumptions!$B$14+Assumptions!$B$15)-25*20*Assumptions!$B$4-(Assumptions!$B$6+Assumptions!$B$7+Assumptions!$B$8) | C21: =50*Assumptions!$B$12-50*(Assumptions!$B$12*Assumptions!$B$14+Assumptions!$B$15)-50*20*Assumptions!$B$4-(Assumptions!$B$6+Assumptions!$B$7+Assumptions!$B$8) | D21: =100*Assumptions!$B$12-100*(Assumptions!$B$12*Assumptions!$B$14+Assumptions!$B$15)-100*20*Assumptions!$B$4-(Assumptions!$B$6+Assumptions!$B$7+Assumptions!$B$8) | E21: =200*Assumptions!$B$12-200*(Assumptions!$B$12*Assumptions!$B$14+Assumptions!$B$15)-200*20*Assumptions!$B$4-(Assumptions!$B$6+Assumptions!$B$7+Assumptions!$B$8) | F21: =400*Assumptions!$B$12-400*(Assumptions!$B$12*Assumptions!$B$14+Assumptions!$B$15)-400*20*Assumptions!$B$4-(Assumptions!$B$6+Assumptions!$B$7+Assumptions!$B$8) | G21: =800*Assumptions!$B$12-800*(Assumptions!$B$12*Assumptions!$B$14+Assumptions!$B$15)-800*20*Assumptions!$B$4-(Assumptions!$B$6+Assumptions!$B$7+Assumptions!$B$8) | H21: =1500*Assumptions!$B$12-1500*(Assumptions!$B$12*Assumptions!$B$14+Assumptions!$B$15)-1500*20*Assumptions!$B$4-(Assumptions!$B$6+Assumptions!$B$7+Assumptions!$B$8) | I21: =3000*Assumptions!$B$12-3000*(Assumptions!$B$12*Assumptions!$B$14+Assumptions!$B$15)-3000*20*Assumptions!$B$4-(Assumptions!$B$6+Assumptions!$B$7+Assumptions!$B$8) | J21: =5000*Assumptions!$B$12-5000*(Assumptions!$B$12*Assumptions!$B$14+Assumptions!$B$15)-5000*20*Assumptions!$B$4-(Assumptions!$B$6+Assumptions!$B$7+Assumptions!$B$8)
A22: 25 | B22: =25*Assumptions!$B$12-25*(Assumptions!$B$12*Assumptions!$B$14+Assumptions!$B$15)-25*25*Assumptions!$B$4-(Assumptions!$B$6+Assumptions!$B$7+Assumptions!$B$8) | C22: =50*Assumptions!$B$12-50*(Assumptions!$B$12*Assumptions!$B$14+Assumptions!$B$15)-50*25*Assumptions!$B$4-(Assumptions!$B$6+Assumptions!$B$7+Assumptions!$B$8) | D22: =100*Assumptions!$B$12-100*(Assumptions!$B$12*Assumptions!$B$14+Assumptions!$B$15)-100*25*Assumptions!$B$4-(Assumptions!$B$6+Assumptions!$B$7+Assumptions!$B$8) | E22: =200*Assumptions!$B$12-200*(Assumptions!$B$12*Assumptions!$B$14+Assumptions!$B$15)-200*25*Assumptions!$B$4-(Assumptions!$B$6+Assumptions!$B$7+Assumptions!$B$8) | F22: =400*Assumptions!$B$12-400*(Assumptions!$B$12*Assumptions!$B$14+Assumptions!$B$15)-400*25*Assumptions!$B$4-(Assumptions!$B$6+Assumptions!$B$7+Assumptions!$B$8) | G22: =800*Assumptions!$B$12-800*(Assumptions!$B$12*Assumptions!$B$14+Assumptions!$B$15)-800*25*Assumptions!$B$4-(Assumptions!$B$6+Assumptions!$B$7+Assumptions!$B$8) | H22: =1500*Assumptions!$B$12-1500*(Assumptions!$B$12*Assumptions!$B$14+Assumptions!$B$15)-1500*25*Assumptions!$B$4-(Assumptions!$B$6+Assumptions!$B$7+Assumptions!$B$8) | I22: =3000*Assumptions!$B$12-3000*(Assumptions!$B$12*Assumptions!$B$14+Assumptions!$B$15)-3000*25*Assumptions!$B$4-(Assumptions!$B$6+Assumptions!$B$7+Assumptions!$B$8) | J22: =5000*Assumptions!$B$12-5000*(Assumptions!$B$12*Assumptions!$B$14+Assumptions!$B$15)-5000*25*Assumptions!$B$4-(Assumptions!$B$6+Assumptions!$B$7+Assumptions!$B$8)
A23: 30 | B23: =25*Assumptions!$B$12-25*(Assumptions!$B$12*Assumptions!$B$14+Assumptions!$B$15)-25*30*Assumptions!$B$4-(Assumptions!$B$6+Assumptions!$B$7+Assumptions!$B$8) | C23: =50*Assumptions!$B$12-50*(Assumptions!$B$12*Assumptions!$B$14+Assumptions!$B$15)-50*30*Assumptions!$B$4-(Assumptions!$B$6+Assumptions!$B$7+Assumptions!$B$8) | D23: =100*Assumptions!$B$12-100*(Assumptions!$B$12*Assumptions!$B$14+Assumptions!$B$15)-100*30*Assumptions!$B$4-(Assumptions!$B$6+Assumptions!$B$7+Assumptions!$B$8) | E23: =200*Assumptions!$B$12-200*(Assumptions!$B$12*Assumptions!$B$14+Assumptions!$B$15)-200*30*Assumptions!$B$4-(Assumptions!$B$6+Assumptions!$B$7+Assumptions!$B$8) | F23: =400*Assumptions!$B$12-400*(Assumptions!$B$12*Assumptions!$B$14+Assumptions!$B$15)-400*30*Assumptions!$B$4-(Assumptions!$B$6+Assumptions!$B$7+Assumptions!$B$8) | G23: =800*Assumptions!$B$12-800*(Assumptions!$B$12*Assumptions!$B$14+Assumptions!$B$15)-800*30*Assumptions!$B$4-(Assumptions!$B$6+Assumptions!$B$7+Assumptions!$B$8) | H23: =1500*Assumptions!$B$12-1500*(Assumptions!$B$12*Assumptions!$B$14+Assumptions!$B$15)-1500*30*Assumptions!$B$4-(Assumptions!$B$6+Assumptions!$B$7+Assumptions!$B$8) | I23: =3000*Assumptions!$B$12-3000*(Assumptions!$B$12*Assumptions!$B$14+Assumptions!$B$15)-3000*30*Assumptions!$B$4-(Assumptions!$B$6+Assumptions!$B$7+Assumptions!$B$8) | J23: =5000*Assumptions!$B$12-5000*(Assumptions!$B$12*Assumptions!$B$14+Assumptions!$B$15)-5000*30*Assumptions!$B$4-(Assumptions!$B$6+Assumptions!$B$7+Assumptions!$B$8)
A24: 35 | B24: =25*Assumptions!$B$12-25*(Assumptions!$B$12*Assumptions!$B$14+Assumptions!$B$15)-25*35*Assumptions!$B$4-(Assumptions!$B$6+Assumptions!$B$7+Assumptions!$B$8) | C24: =50*Assumptions!$B$12-50*(Assumptions!$B$12*Assumptions!$B$14+Assumptions!$B$15)-50*35*Assumptions!$B$4-(Assumptions!$B$6+Assumptions!$B$7+Assumptions!$B$8) | D24: =100*Assumptions!$B$12-100*(Assumptions!$B$12*Assumptions!$B$14+Assumptions!$B$15)-100*35*Assumptions!$B$4-(Assumptions!$B$6+Assumptions!$B$7+Assumptions!$B$8) | E24: =200*Assumptions!$B$12-200*(Assumptions!$B$12*Assumptions!$B$14+Assumptions!$B$15)-200*35*Assumptions!$B$4-(Assumptions!$B$6+Assumptions!$B$7+Assumptions!$B$8) | F24: =400*Assumptions!$B$12-400*(Assumptions!$B$12*Assumptions!$B$14+Assumptions!$B$15)-400*35*Assumptions!$B$4-(Assumptions!$B$6+Assumptions!$B$7+Assumptions!$B$8) | G24: =800*Assumptions!$B$12-800*(Assumptions!$B$12*Assumptions!$B$14+Assumptions!$B$15)-800*35*Assumptions!$B$4-(Assumptions!$B$6+Assumptions!$B$7+Assumptions!$B$8) | H24: =1500*Assumptions!$B$12-1500*(Assumptions!$B$12*Assumptions!$B$14+Assumptions!$B$15)-1500*35*Assumptions!$B$4-(Assumptions!$B$6+Assumptions!$B$7+Assumptions!$B$8) | I24: =3000*Assumptions!$B$12-3000*(Assumptions!$B$12*Assumptions!$B$14+Assumptions!$B$15)-3000*35*Assumptions!$B$4-(Assumptions!$B$6+Assumptions!$B$7+Assumptions!$B$8) | J24: =5000*Assumptions!$B$12-5000*(Assumptions!$B$12*Assumptions!$B$14+Assumptions!$B$15)-5000*35*Assumptions!$B$4-(Assumptions!$B$6+Assumptions!$B$7+Assumptions!$B$8)
A25: 40 | B25: =25*Assumptions!$B$12-25*(Assumptions!$B$12*Assumptions!$B$14+Assumptions!$B$15)-25*40*Assumptions!$B$4-(Assumptions!$B$6+Assumptions!$B$7+Assumptions!$B$8) | C25: =50*Assumptions!$B$12-50*(Assumptions!$B$12*Assumptions!$B$14+Assumptions!$B$15)-50*40*Assumptions!$B$4-(Assumptions!$B$6+Assumptions!$B$7+Assumptions!$B$8) | D25: =100*Assumptions!$B$12-100*(Assumptions!$B$12*Assumptions!$B$14+Assumptions!$B$15)-100*40*Assumptions!$B$4-(Assumptions!$B$6+Assumptions!$B$7+Assumptions!$B$8) | E25: =200*Assumptions!$B$12-200*(Assumptions!$B$12*Assumptions!$B$14+Assumptions!$B$15)-200*40*Assumptions!$B$4-(Assumptions!$B$6+Assumptions!$B$7+Assumptions!$B$8) | F25: =400*Assumptions!$B$12-400*(Assumptions!$B$12*Assumptions!$B$14+Assumptions!$B$15)-400*40*Assumptions!$B$4-(Assumptions!$B$6+Assumptions!$B$7+Assumptions!$B$8) | G25: =800*Assumptions!$B$12-800*(Assumptions!$B$12*Assumptions!$B$14+Assumptions!$B$15)-800*40*Assumptions!$B$4-(Assumptions!$B$6+Assumptions!$B$7+Assumptions!$B$8) | H25: =1500*Assumptions!$B$12-1500*(Assumptions!$B$12*Assumptions!$B$14+Assumptions!$B$15)-1500*40*Assumptions!$B$4-(Assumptions!$B$6+Assumptions!$B$7+Assumptions!$B$8) | I25: =3000*Assumptions!$B$12-3000*(Assumptions!$B$12*Assumptions!$B$14+Assumptions!$B$15)-3000*40*Assumptions!$B$4-(Assumptions!$B$6+Assumptions!$B$7+Assumptions!$B$8) | J25: =5000*Assumptions!$B$12-5000*(Assumptions!$B$12*Assumptions!$B$14+Assumptions!$B$15)-5000*40*Assumptions!$B$4-(Assumptions!$B$6+Assumptions!$B$7+Assumptions!$B$8)
A26: 45 | B26: =25*Assumptions!$B$12-25*(Assumptions!$B$12*Assumptions!$B$14+Assumptions!$B$15)-25*45*Assumptions!$B$4-(Assumptions!$B$6+Assumptions!$B$7+Assumptions!$B$8) | C26: =50*Assumptions!$B$12-50*(Assumptions!$B$12*Assumptions!$B$14+Assumptions!$B$15)-50*45*Assumptions!$B$4-(Assumptions!$B$6+Assumptions!$B$7+Assumptions!$B$8) | D26: =100*Assumptions!$B$12-100*(Assumptions!$B$12*Assumptions!$B$14+Assumptions!$B$15)-100*45*Assumptions!$B$4-(Assumptions!$B$6+Assumptions!$B$7+Assumptions!$B$8) | E26: =200*Assumptions!$B$12-200*(Assumptions!$B$12*Assumptions!$B$14+Assumptions!$B$15)-200*45*Assumptions!$B$4-(Assumptions!$B$6+Assumptions!$B$7+Assumptions!$B$8) | F26: =400*Assumptions!$B$12-400*(Assumptions!$B$12*Assumptions!$B$14+Assumptions!$B$15)-400*45*Assumptions!$B$4-(Assumptions!$B$6+Assumptions!$B$7+Assumptions!$B$8) | G26: =800*Assumptions!$B$12-800*(Assumptions!$B$12*Assumptions!$B$14+Assumptions!$B$15)-800*45*Assumptions!$B$4-(Assumptions!$B$6+Assumptions!$B$7+Assumptions!$B$8) | H26: =1500*Assumptions!$B$12-1500*(Assumptions!$B$12*Assumptions!$B$14+Assumptions!$B$15)-1500*45*Assumptions!$B$4-(Assumptions!$B$6+Assumptions!$B$7+Assumptions!$B$8) | I26: =3000*Assumptions!$B$12-3000*(Assumptions!$B$12*Assumptions!$B$14+Assumptions!$B$15)-3000*45*Assumptions!$B$4-(Assumptions!$B$6+Assumptions!$B$7+Assumptions!$B$8) | J26: =5000*Assumptions!$B$12-5000*(Assumptions!$B$12*Assumptions!$B$14+Assumptions!$B$15)-5000*45*Assumptions!$B$4-(Assumptions!$B$6+Assumptions!$B$7+Assumptions!$B$8)
A29: (C) OpenAI Realtime — no Enterprise tier modeled
A30: Avg min/sub ↓ | Subscribers → | B30: 25 | C30: 50 | D30: 100 | E30: 200 | F30: 400 | G30: 800 | H30: 1500 | I30: 3000 | J30: 5000
A31: 10 | B31: =25*Assumptions!$B$12-25*(Assumptions!$B$12*Assumptions!$B$14+Assumptions!$B$15)-25*10*Assumptions!$B$5-(Assumptions!$B$7+Assumptions!$B$8) | C31: =50*Assumptions!$B$12-50*(Assumptions!$B$12*Assumptions!$B$14+Assumptions!$B$15)-50*10*Assumptions!$B$5-(Assumptions!$B$7+Assumptions!$B$8) | D31: =100*Assumptions!$B$12-100*(Assumptions!$B$12*Assumptions!$B$14+Assumptions!$B$15)-100*10*Assumptions!$B$5-(Assumptions!$B$7+Assumptions!$B$8) | E31: =200*Assumptions!$B$12-200*(Assumptions!$B$12*Assumptions!$B$14+Assumptions!$B$15)-200*10*Assumptions!$B$5-(Assumptions!$B$7+Assumptions!$B$8) | F31: =400*Assumptions!$B$12-400*(Assumptions!$B$12*Assumptions!$B$14+Assumptions!$B$15)-400*10*Assumptions!$B$5-(Assumptions!$B$7+Assumptions!$B$8) | G31: =800*Assumptions!$B$12-800*(Assumptions!$B$12*Assumptions!$B$14+Assumptions!$B$15)-800*10*Assumptions!$B$5-(Assumptions!$B$7+Assumptions!$B$8) | H31: =1500*Assumptions!$B$12-1500*(Assumptions!$B$12*Assumptions!$B$14+Assumptions!$B$15)-1500*10*Assumptions!$B$5-(Assumptions!$B$7+Assumptions!$B$8) | I31: =3000*Assumptions!$B$12-3000*(Assumptions!$B$12*Assumptions!$B$14+Assumptions!$B$15)-3000*10*Assumptions!$B$5-(Assumptions!$B$7+Assumptions!$B$8) | J31: =5000*Assumptions!$B$12-5000*(Assumptions!$B$12*Assumptions!$B$14+Assumptions!$B$15)-5000*10*Assumptions!$B$5-(Assumptions!$B$7+Assumptions!$B$8)
A32: 15 | B32: =25*Assumptions!$B$12-25*(Assumptions!$B$12*Assumptions!$B$14+Assumptions!$B$15)-25*15*Assumptions!$B$5-(Assumptions!$B$7+Assumptions!$B$8) | C32: =50*Assumptions!$B$12-50*(Assumptions!$B$12*Assumptions!$B$14+Assumptions!$B$15)-50*15*Assumptions!$B$5-(Assumptions!$B$7+Assumptions!$B$8) | D32: =100*Assumptions!$B$12-100*(Assumptions!$B$12*Assumptions!$B$14+Assumptions!$B$15)-100*15*Assumptions!$B$5-(Assumptions!$B$7+Assumptions!$B$8) | E32: =200*Assumptions!$B$12-200*(Assumptions!$B$12*Assumptions!$B$14+Assumptions!$B$15)-200*15*Assumptions!$B$5-(Assumptions!$B$7+Assumptions!$B$8) | F32: =400*Assumptions!$B$12-400*(Assumptions!$B$12*Assumptions!$B$14+Assumptions!$B$15)-400*15*Assumptions!$B$5-(Assumptions!$B$7+Assumptions!$B$8) | G32: =800*Assumptions!$B$12-800*(Assumptions!$B$12*Assumptions!$B$14+Assumptions!$B$15)-800*15*Assumptions!$B$5-(Assumptions!$B$7+Assumptions!$B$8) | H32: =1500*Assumptions!$B$12-1500*(Assumptions!$B$12*Assumptions!$B$14+Assumptions!$B$15)-1500*15*Assumptions!$B$5-(Assumptions!$B$7+Assumptions!$B$8) | I32: =3000*Assumptions!$B$12-3000*(Assumptions!$B$12*Assumptions!$B$14+Assumptions!$B$15)-3000*15*Assumptions!$B$5-(Assumptions!$B$7+Assumptions!$B$8) | J32: =5000*Assumptions!$B$12-5000*(Assumptions!$B$12*Assumptions!$B$14+Assumptions!$B$15)-5000*15*Assumptions!$B$5-(Assumptions!$B$7+Assumptions!$B$8)
A33: 20 | B33: =25*Assumptions!$B$12-25*(Assumptions!$B$12*Assumptions!$B$14+Assumptions!$B$15)-25*20*Assumptions!$B$5-(Assumptions!$B$7+Assumptions!$B$8) | C33: =50*Assumptions!$B$12-50*(Assumptions!$B$12*Assumptions!$B$14+Assumptions!$B$15)-50*20*Assumptions!$B$5-(Assumptions!$B$7+Assumptions!$B$8) | D33: =100*Assumptions!$B$12-100*(Assumptions!$B$12*Assumptions!$B$14+Assumptions!$B$15)-100*20*Assumptions!$B$5-(Assumptions!$B$7+Assumptions!$B$8) | E33: =200*Assumptions!$B$12-200*(Assumptions!$B$12*Assumptions!$B$14+Assumptions!$B$15)-200*20*Assumptions!$B$5-(Assumptions!$B$7+Assumptions!$B$8) | F33: =400*Assumptions!$B$12-400*(Assumptions!$B$12*Assumptions!$B$14+Assumptions!$B$15)-400*20*Assumptions!$B$5-(Assumptions!$B$7+Assumptions!$B$8) | G33: =800*Assumptions!$B$12-800*(Assumptions!$B$12*Assumptions!$B$14+Assumptions!$B$15)-800*20*Assumptions!$B$5-(Assumptions!$B$7+Assumptions!$B$8) | H33: =1500*Assumptions!$B$12-1500*(Assumptions!$B$12*Assumptions!$B$14+Assumptions!$B$15)-1500*20*Assumptions!$B$5-(Assumptions!$B$7+Assumptions!$B$8) | I33: =3000*Assumptions!$B$12-3000*(Assumptions!$B$12*Assumptions!$B$14+Assumptions!$B$15)-3000*20*Assumptions!$B$5-(Assumptions!$B$7+Assumptions!$B$8) | J33: =5000*Assumptions!$B$12-5000*(Assumptions!$B$12*Assumptions!$B$14+Assumptions!$B$15)-5000*20*Assumptions!$B$5-(Assumptions!$B$7+Assumptions!$B$8)
A34: 25 | B34: =25*Assumptions!$B$12-25*(Assumptions!$B$12*Assumptions!$B$14+Assumptions!$B$15)-25*25*Assumptions!$B$5-(Assumptions!$B$7+Assumptions!$B$8) | C34: =50*Assumptions!$B$12-50*(Assumptions!$B$12*Assumptions!$B$14+Assumptions!$B$15)-50*25*Assumptions!$B$5-(Assumptions!$B$7+Assumptions!$B$8) | D34: =100*Assumptions!$B$12-100*(Assumptions!$B$12*Assumptions!$B$14+Assumptions!$B$15)-100*25*Assumptions!$B$5-(Assumptions!$B$7+Assumptions!$B$8) | E34: =200*Assumptions!$B$12-200*(Assumptions!$B$12*Assumptions!$B$14+Assumptions!$B$15)-200*25*Assumptions!$B$5-(Assumptions!$B$7+Assumptions!$B$8) | F34: =400*Assumptions!$B$12-400*(Assumptions!$B$12*Assumptions!$B$14+Assumptions!$B$15)-400*25*Assumptions!$B$5-(Assumptions!$B$7+Assumptions!$B$8) | G34: =800*Assumptions!$B$12-800*(Assumptions!$B$12*Assumptions!$B$14+Assumptions!$B$15)-800*25*Assumptions!$B$5-(Assumptions!$B$7+Assumptions!$B$8) | H34: =1500*Assumptions!$B$12-1500*(Assumptions!$B$12*Assumptions!$B$14+Assumptions!$B$15)-1500*25*Assumptions!$B$5-(Assumptions!$B$7+Assumptions!$B$8) | I34: =3000*Assumptions!$B$12-3000*(Assumptions!$B$12*Assumptions!$B$14+Assumptions!$B$15)-3000*25*Assumptions!$B$5-(Assumptions!$B$7+Assumptions!$B$8) | J34: =5000*Assumptions!$B$12-5000*(Assumptions!$B$12*Assumptions!$B$14+Assumptions!$B$15)-5000*25*Assumptions!$B$5-(Assumptions!$B$7+Assumptions!$B$8)
A35: 30 | B35: =25*Assumptions!$B$12-25*(Assumptions!$B$12*Assumptions!$B$14+Assumptions!$B$15)-25*30*Assumptions!$B$5-(Assumptions!$B$7+Assumptions!$B$8) | C35: =50*Assumptions!$B$12-50*(Assumptions!$B$12*Assumptions!$B$14+Assumptions!$B$15)-50*30*Assumptions!$B$5-(Assumptions!$B$7+Assumptions!$B$8) | D35: =100*Assumptions!$B$12-100*(Assumptions!$B$12*Assumptions!$B$14+Assumptions!$B$15)-100*30*Assumptions!$B$5-(Assumptions!$B$7+Assumptions!$B$8) | E35: =200*Assumptions!$B$12-200*(Assumptions!$B$12*Assumptions!$B$14+Assumptions!$B$15)-200*30*Assumptions!$B$5-(Assumptions!$B$7+Assumptions!$B$8) | F35: =400*Assumptions!$B$12-400*(Assumptions!$B$12*Assumptions!$B$14+Assumptions!$B$15)-400*30*Assumptions!$B$5-(Assumptions!$B$7+Assumptions!$B$8) | G35: =800*Assumptions!$B$12-800*(Assumptions!$B$12*Assumptions!$B$14+Assumptions!$B$15)-800*30*Assumptions!$B$5-(Assumptions!$B$7+Assumptions!$B$8) | H35: =1500*Assumptions!$B$12-1500*(Assumptions!$B$12*Assumptions!$B$14+Assumptions!$B$15)-1500*30*Assumptions!$B$5-(Assumptions!$B$7+Assumptions!$B$8) | I35: =3000*Assumptions!$B$12-3000*(Assumptions!$B$12*Assumptions!$B$14+Assumptions!$B$15)-3000*30*Assumptions!$B$5-(Assumptions!$B$7+Assumptions!$B$8) | J35: =5000*Assumptions!$B$12-5000*(Assumptions!$B$12*Assumptions!$B$14+Assumptions!$B$15)-5000*30*Assumptions!$B$5-(Assumptions!$B$7+Assumptions!$B$8)
A36: 35 | B36: =25*Assumptions!$B$12-25*(Assumptions!$B$12*Assumptions!$B$14+Assumptions!$B$15)-25*35*Assumptions!$B$5-(Assumptions!$B$7+Assumptions!$B$8) | C36: =50*Assumptions!$B$12-50*(Assumptions!$B$12*Assumptions!$B$14+Assumptions!$B$15)-50*35*Assumptions!$B$5-(Assumptions!$B$7+Assumptions!$B$8) | D36: =100*Assumptions!$B$12-100*(Assumptions!$B$12*Assumptions!$B$14+Assumptions!$B$15)-100*35*Assumptions!$B$5-(Assumptions!$B$7+Assumptions!$B$8) | E36: =200*Assumptions!$B$12-200*(Assumptions!$B$12*Assumptions!$B$14+Assumptions!$B$15)-200*35*Assumptions!$B$5-(Assumptions!$B$7+Assumptions!$B$8) | F36: =400*Assumptions!$B$12-400*(Assumptions!$B$12*Assumptions!$B$14+Assumptions!$B$15)-400*35*Assumptions!$B$5-(Assumptions!$B$7+Assumptions!$B$8) | G36: =800*Assumptions!$B$12-800*(Assumptions!$B$12*Assumptions!$B$14+Assumptions!$B$15)-800*35*Assumptions!$B$5-(Assumptions!$B$7+Assumptions!$B$8) | H36: =1500*Assumptions!$B$12-1500*(Assumptions!$B$12*Assumptions!$B$14+Assumptions!$B$15)-1500*35*Assumptions!$B$5-(Assumptions!$B$7+Assumptions!$B$8) | I36: =3000*Assumptions!$B$12-3000*(Assumptions!$B$12*Assumptions!$B$14+Assumptions!$B$15)-3000*35*Assumptions!$B$5-(Assumptions!$B$7+Assumptions!$B$8) | J36: =5000*Assumptions!$B$12-5000*(Assumptions!$B$12*Assumptions!$B$14+Assumptions!$B$15)-5000*35*Assumptions!$B$5-(Assumptions!$B$7+Assumptions!$B$8)
A37: 40 | B37: =25*Assumptions!$B$12-25*(Assumptions!$B$12*Assumptions!$B$14+Assumptions!$B$15)-25*40*Assumptions!$B$5-(Assumptions!$B$7+Assumptions!$B$8) | C37: =50*Assumptions!$B$12-50*(Assumptions!$B$12*Assumptions!$B$14+Assumptions!$B$15)-50*40*Assumptions!$B$5-(Assumptions!$B$7+Assumptions!$B$8) | D37: =100*Assumptions!$B$12-100*(Assumptions!$B$12*Assumptions!$B$14+Assumptions!$B$15)-100*40*Assumptions!$B$5-(Assumptions!$B$7+Assumptions!$B$8) | E37: =200*Assumptions!$B$12-200*(Assumptions!$B$12*Assumptions!$B$14+Assumptions!$B$15)-200*40*Assumptions!$B$5-(Assumptions!$B$7+Assumptions!$B$8) | F37: =400*Assumptions!$B$12-400*(Assumptions!$B$12*Assumptions!$B$14+Assumptions!$B$15)-400*40*Assumptions!$B$5-(Assumptions!$B$7+Assumptions!$B$8) | G37: =800*Assumptions!$B$12-800*(Assumptions!$B$12*Assumptions!$B$14+Assumptions!$B$15)-800*40*Assumptions!$B$5-(Assumptions!$B$7+Assumptions!$B$8) | H37: =1500*Assumptions!$B$12-1500*(Assumptions!$B$12*Assumptions!$B$14+Assumptions!$B$15)-1500*40*Assumptions!$B$5-(Assumptions!$B$7+Assumptions!$B$8) | I37: =3000*Assumptions!$B$12-3000*(Assumptions!$B$12*Assumptions!$B$14+Assumptions!$B$15)-3000*40*Assumptions!$B$5-(Assumptions!$B$7+Assumptions!$B$8) | J37: =5000*Assumptions!$B$12-5000*(Assumptions!$B$12*Assumptions!$B$14+Assumptions!$B$15)-5000*40*Assumptions!$B$5-(Assumptions!$B$7+Assumptions!$B$8)
A38: 45 | B38: =25*Assumptions!$B$12-25*(Assumptions!$B$12*Assumptions!$B$14+Assumptions!$B$15)-25*45*Assumptions!$B$5-(Assumptions!$B$7+Assumptions!$B$8) | C38: =50*Assumptions!$B$12-50*(Assumptions!$B$12*Assumptions!$B$14+Assumptions!$B$15)-50*45*Assumptions!$B$5-(Assumptions!$B$7+Assumptions!$B$8) | D38: =100*Assumptions!$B$12-100*(Assumptions!$B$12*Assumptions!$B$14+Assumptions!$B$15)-100*45*Assumptions!$B$5-(Assumptions!$B$7+Assumptions!$B$8) | E38: =200*Assumptions!$B$12-200*(Assumptions!$B$12*Assumptions!$B$14+Assumptions!$B$15)-200*45*Assumptions!$B$5-(Assumptions!$B$7+Assumptions!$B$8) | F38: =400*Assumptions!$B$12-400*(Assumptions!$B$12*Assumptions!$B$14+Assumptions!$B$15)-400*45*Assumptions!$B$5-(Assumptions!$B$7+Assumptions!$B$8) | G38: =800*Assumptions!$B$12-800*(Assumptions!$B$12*Assumptions!$B$14+Assumptions!$B$15)-800*45*Assumptions!$B$5-(Assumptions!$B$7+Assumptions!$B$8) | H38: =1500*Assumptions!$B$12-1500*(Assumptions!$B$12*Assumptions!$B$14+Assumptions!$B$15)-1500*45*Assumptions!$B$5-(Assumptions!$B$7+Assumptions!$B$8) | I38: =3000*Assumptions!$B$12-3000*(Assumptions!$B$12*Assumptions!$B$14+Assumptions!$B$15)-3000*45*Assumptions!$B$5-(Assumptions!$B$7+Assumptions!$B$8) | J38: =5000*Assumptions!$B$12-5000*(Assumptions!$B$12*Assumptions!$B$14+Assumptions!$B$15)-5000*45*Assumptions!$B$5-(Assumptions!$B$7+Assumptions!$B$8)
A41: Reading the tables
A42: • Green cells = profitable at that scale. Red = losing money.
A43: • Compare (A) vs (B): the Enterprise/BAA fixed cost requires ~150–200 subs to absorb. If you can't get there in year 1, stay educational-only and skip Enterprise.
A44: • Compare (B) vs (C): same usage, OpenAI Realtime needs 2–3× more subscribers to break even.
A45: • The 'cliff' at high usage on the OpenAI table shows why pricing/cap matters: a free-for-all minutes policy on OpenAI Realtime bankrupts you.

Sheet 12-Month Projection
A1: 12-Month Projection — ElevenLabs (with Enterprise/BAA) vs OpenAI Realtime
A3: Subscriber growth curve (yellow = editable)
A4: Month | B4: M1 | C4: M2 | D4: M3 | E4: M4 | F4: M5 | G4: M6 | H4: M7 | I4: M8 | J4: M9 | K4: M10 | L4: M11 | M4: M12
A5: Active subscribers | B5: 10 | C5: 25 | D5: 50 | E5: 90 | F5: 150 | G5: 230 | H5: 330 | I5: 450 | J5: 580 | K5: 720 | L5: 850 | M5: 950
A7: Scenario A: ElevenLabs Agents WITH Enterprise + BAA
A8: Revenue | B8: =B5*Assumptions!$B$12 | C8: =C5*Assumptions!$B$12 | D8: =D5*Assumptions!$B$12 | E8: =E5*Assumptions!$B$12 | F8: =F5*Assumptions!$B$12 | G8: =G5*Assumptions!$B$12 | H8: =H5*Assumptions!$B$12 | I8: =I5*Assumptions!$B$12 | ... M8: =M5*Assumptions!$B$12
A9: Variable cost (conversation) | B9: =-B5*Assumptions!$B$19*Assumptions!$B$4 | C9: =-C5*Assumptions!$B$19*Assumptions!$B$4 | D9: =-D5*Assumptions!$B$19*Assumptions!$B$4 | E9: =-E5*Assumptions!$B$19*Assumptions!$B$4 | F9: =-F5*Assumptions!$B$19*Assumptions!$B$4 | G9: =-G5*Assumptions!$B$19*Assumptions!$B$4 | H9: =-H5*Assumptions!$B$19*Assumptions!$B$4 | I9: =-I5*Assumptions!$B$19*Assumptions!$B$4 | ... M9: =-M5*Assumptions!$B$19*Assumptions!$B$4
A10: Stripe fees | B10: =-B5*(Assumptions!$B$12*Assumptions!$B$14+Assumptions!$B$15) | C10: =-C5*(Assumptions!$B$12*Assumptions!$B$14+Assumptions!$B$15) | D10: =-D5*(Assumptions!$B$12*Assumptions!$B$14+Assumptions!$B$15) | E10: =-E5*(Assumptions!$B$12*Assumptions!$B$14+Assumptions!$B$15) | F10: =-F5*(Assumptions!$B$12*Assumptions!$B$14+Assumptions!$B$15) | G10: =-G5*(Assumptions!$B$12*Assumptions!$B$14+Assumptions!$B$15) | H10: =-H5*(Assumptions!$B$12*Assumptions!$B$14+Assumptions!$B$15) | I10: =-I5*(Assumptions!$B$12*Assumptions!$B$14+Assumptions!$B$15) | ... M10: =-M5*(Assumptions!$B$12*Assumptions!$B$14+Assumptions!$B$15)
A11: Fixed (Enterprise + hosting + support) | B11: =-(Assumptions!$B$6+Assumptions!$B$7+Assumptions!$B$8) | C11: =-(Assumptions!$B$6+Assumptions!$B$7+Assumptions!$B$8) | D11: =-(Assumptions!$B$6+Assumptions!$B$7+Assumptions!$B$8) | E11: =-(Assumptions!$B$6+Assumptions!$B$7+Assumptions!$B$8) | F11: =-(Assumptions!$B$6+Assumptions!$B$7+Assumptions!$B$8) | G11: =-(Assumptions!$B$6+Assumptions!$B$7+Assumptions!$B$8) | H11: =-(Assumptions!$B$6+Assumptions!$B$7+Assumptions!$B$8) | I11: =-(Assumptions!$B$6+Assumptions!$B$7+Assumptions!$B$8) | ... M11: =-(Assumptions!$B$6+Assumptions!$B$7+Assumptions!$B$8)
A12: Monthly net profit | B12: =B8+B9+B10+B11 | C12: =C8+C9+C10+C11 | D12: =D8+D9+D10+D11 | E12: =E8+E9+E10+E11 | F12: =F8+F9+F10+F11 | G12: =G8+G9+G10+G11 | H12: =H8+H9+H10+H11 | I12: =I8+I9+I10+I11 | ... M12: =M8+M9+M10+M11
A13: Cumulative profit | B13: =B12 | C13: =B13+C12 | D13: =C13+D12 | E13: =D13+E12 | F13: =E13+F12 | G13: =F13+G12 | H13: =G13+H12 | I13: =H13+I12 | J13: =I13+J12 | ... M13: =L13+M12
A15: Scenario B: ElevenLabs Agents WITHOUT Enterprise (educational-only positioning)
A16: Revenue | B16: =B5*Assumptions!$B$12 | C16: =C5*Assumptions!$B$12 | D16: =D5*Assumptions!$B$12 | E16: =E5*Assumptions!$B$12 | F16: =F5*Assumptions!$B$12 | G16: =G5*Assumptions!$B$12 | H16: =H5*Assumptions!$B$12 | I16: =I5*Assumptions!$B$12 | ... M16: =M5*Assumptions!$B$12
A17: Variable cost (conversation) | B17: =-B5*Assumptions!$B$19*Assumptions!$B$4 | C17: =-C5*Assumptions!$B$19*Assumptions!$B$4 | D17: =-D5*Assumptions!$B$19*Assumptions!$B$4 | E17: =-E5*Assumptions!$B$19*Assumptions!$B$4 | F17: =-F5*Assumptions!$B$19*Assumptions!$B$4 | G17: =-G5*Assumptions!$B$19*Assumptions!$B$4 | H17: =-H5*Assumptions!$B$19*Assumptions!$B$4 | I17: =-I5*Assumptions!$B$19*Assumptions!$B$4 | ... M17: =-M5*Assumptions!$B$19*Assumptions!$B$4
A18: Stripe fees | B18: =-B5*(Assumptions!$B$12*Assumptions!$B$14+Assumptions!$B$15) | C18: =-C5*(Assumptions!$B$12*Assumptions!$B$14+Assumptions!$B$15) | D18: =-D5*(Assumptions!$B$12*Assumptions!$B$14+Assumptions!$B$15) | E18: =-E5*(Assumptions!$B$12*Assumptions!$B$14+Assumptions!$B$15) | F18: =-F5*(Assumptions!$B$12*Assumptions!$B$14+Assumptions!$B$15) | G18: =-G5*(Assumptions!$B$12*Assumptions!$B$14+Assumptions!$B$15) | H18: =-H5*(Assumptions!$B$12*Assumptions!$B$14+Assumptions!$B$15) | I18: =-I5*(Assumptions!$B$12*Assumptions!$B$14+Assumptions!$B$15) | ... M18: =-M5*(Assumptions!$B$12*Assumptions!$B$14+Assumptions!$B$15)
A19: Fixed (hosting + support) | B19: =-(Assumptions!$B$7+Assumptions!$B$8) | C19: =-(Assumptions!$B$7+Assumptions!$B$8) | D19: =-(Assumptions!$B$7+Assumptions!$B$8) | E19: =-(Assumptions!$B$7+Assumptions!$B$8) | F19: =-(Assumptions!$B$7+Assumptions!$B$8) | G19: =-(Assumptions!$B$7+Assumptions!$B$8) | H19: =-(Assumptions!$B$7+Assumptions!$B$8) | I19: =-(Assumptions!$B$7+Assumptions!$B$8) | ... M19: =-(Assumptions!$B$7+Assumptions!$B$8)
A20: Monthly net profit | B20: =B16+B17+B18+B19 | C20: =C16+C17+C18+C19 | D20: =D16+D17+D18+D19 | E20: =E16+E17+E18+E19 | F20: =F16+F17+F18+F19 | G20: =G16+G17+G18+G19 | H20: =H16+H17+H18+H19 | I20: =I16+I17+I18+I19 | ... M20: =M16+M17+M18+M19
A21: Cumulative profit | B21: =B20 | C21: =B21+C20 | D21: =C21+D20 | E21: =D21+E20 | F21: =E21+F20 | G21: =F21+G20 | H21: =G21+H20 | I21: =H21+I20 | J21: =I21+J20 | ... M21: =L21+M20
A23: Scenario C: OpenAI Realtime (no Enterprise modeled)
A24: Revenue | B24: =B5*Assumptions!$B$12 | C24: =C5*Assumptions!$B$12 | D24: =D5*Assumptions!$B$12 | E24: =E5*Assumptions!$B$12 | F24: =F5*Assumptions!$B$12 | G24: =G5*Assumptions!$B$12 | H24: =H5*Assumptions!$B$12 | I24: =I5*Assumptions!$B$12 | ... M24: =M5*Assumptions!$B$12
A25: Variable cost (conversation) | B25: =-B5*Assumptions!$B$19*Assumptions!$B$5 | C25: =-C5*Assumptions!$B$19*Assumptions!$B$5 | D25: =-D5*Assumptions!$B$19*Assumptions!$B$5 | E25: =-E5*Assumptions!$B$19*Assumptions!$B$5 | F25: =-F5*Assumptions!$B$19*Assumptions!$B$5 | G25: =-G5*Assumptions!$B$19*Assumptions!$B$5 | H25: =-H5*Assumptions!$B$19*Assumptions!$B$5 | I25: =-I5*Assumptions!$B$19*Assumptions!$B$5 | ... M25: =-M5*Assumptions!$B$19*Assumptions!$B$5
A26: Stripe fees | B26: =-B5*(Assumptions!$B$12*Assumptions!$B$14+Assumptions!$B$15) | C26: =-C5*(Assumptions!$B$12*Assumptions!$B$14+Assumptions!$B$15) | D26: =-D5*(Assumptions!$B$12*Assumptions!$B$14+Assumptions!$B$15) | E26: =-E5*(Assumptions!$B$12*Assumptions!$B$14+Assumptions!$B$15) | F26: =-F5*(Assumptions!$B$12*Assumptions!$B$14+Assumptions!$B$15) | G26: =-G5*(Assumptions!$B$12*Assumptions!$B$14+Assumptions!$B$15) | H26: =-H5*(Assumptions!$B$12*Assumptions!$B$14+Assumptions!$B$15) | I26: =-I5*(Assumptions!$B$12*Assumptions!$B$14+Assumptions!$B$15) | ... M26: =-M5*(Assumptions!$B$12*Assumptions!$B$14+Assumptions!$B$15)
A27: Fixed (hosting + support) | B27: =-(Assumptions!$B$7+Assumptions!$B$8) | C27: =-(Assumptions!$B$7+Assumptions!$B$8) | D27: =-(Assumptions!$B$7+Assumptions!$B$8) | E27: =-(Assumptions!$B$7+Assumptions!$B$8) | F27: =-(Assumptions!$B$7+Assumptions!$B$8) | G27: =-(Assumptions!$B$7+Assumptions!$B$8) | H27: =-(Assumptions!$B$7+Assumptions!$B$8) | I27: =-(Assumptions!$B$7+Assumptions!$B$8) | ... M27: =-(Assumptions!$B$7+Assumptions!$B$8)
A28: Monthly net profit | B28: =B24+B25+B26+B27 | C28: =C24+C25+C26+C27 | D28: =D24+D25+D26+D27 | E28: =E24+E25+E26+E27 | F28: =F24+F25+F26+F27 | G28: =G24+G25+G26+G27 | H28: =H24+H25+H26+H27 | I28: =I24+I25+I26+I27 | ... M28: =M24+M25+M26+M27
A29: Cumulative profit | B29: =B28 | C29: =B29+C28 | D29: =C29+D28 | E29: =D29+E28 | F29: =E29+F28 | G29: =F29+G28 | H29: =G29+H28 | I29: =H29+I28 | J29: =I29+J28 | ... M29: =L29+M28
A31: Interpretation: the cumulative-profit row tells you when each scenario becomes self-sustaining. Edit the 'Active subscribers' row to model your own growth assumption. Edit Assumptions sheet for pricing/cost knobs.
